UART_RX.v
/*
UART_RX module to UART bytes from MIDI
- 115200 baud rate 
- 8 data bits (7 for MIDI note and 1 for On/OFF)
- 0 parity bits
- 1 stop bit
- no flow control
CLKS_PER_BIT = CLK_FREQUNECY/BAUDRATE
*/
module UART_RX #(parameter CLKS_PER_BIT = 217)(
    input           i_Clk, 
    input           i_RX_Serial,
    output          o_RX_DV, // pulse to indicate data valid or not
    output [7:0]    o_RX_Byte
    );

    // States of the State machine (Values of RX_State_machine )
    localparam IDLE         = 3'b000; 
    localparam RX_START_BIT = 3'b001; 
    localparam RX_DATA_BIT  = 3'b010; // 217/2 clock cycles
    localparam RX_STOP_BIT  = 3'b011;
    localparam CLEANUP      = 3'b100; 

    reg [7:0]     r_Clock_Count = 0;
    reg [2:0]     r_Bit_Index   = 0; //8 bits total
    reg [7:0]     r_RX_Byte     = 0;
    reg           r_RX_DV       = 0;
    reg [2:0]     r_SM_Main     = 0;


    always @(posedge i_Clk) begin
        case(r_SM_Main)
                IDLE: // State 1 -> Waiting for Serial 
                    begin
                        r_RX_DV       <= 1'b0;
                        r_Clock_Count <= 0;
                        r_Bit_Index   <= 0;
                        
                        if (i_RX_Serial == 1'b0) // Start bit detected
                            r_SM_Main <= RX_START_BIT; // Transition to next state
                        else
                            r_SM_Main <= IDLE;
                    end
                RX_START_BIT: // State 2 - Start bit has been detected (Falling edge of start bit)
                    begin
                        if (r_Clock_Count == (CLKS_PER_BIT-1)/2)
                        begin
                            if (i_RX_Serial == 1'b0)
                                begin
                                    r_Clock_Count <= 0;  // reset counter, found the middle
                                    r_SM_Main     <= RX_DATA_BIT;
                                end
                            else
                                r_SM_Main <= IDLE;
                        end
                    
                        else
                            begin
                                r_Clock_Count <= r_Clock_Count + 1;
                                r_SM_Main     <= RX_START_BIT;
                            end
                    end
                RX_DATA_BIT:
                    begin
                        if (r_Clock_Count < CLKS_PER_BIT-1)
                        begin
                            r_Clock_Count <= r_Clock_Count+1; 
                            r_SM_Main <= r_SM_Main; // stay in the stame state until have a enough clock cycles have elasped
                        end
                        else
                        begin
                            //Enough clock cycles have elapsed for new data bit to appear
                            r_Clock_Count <= 0; 
                            r_RX_Byte[r_Bit_Index] <= i_RX_Serial; // Captuing the bit
                            // Check number of data bits recieved to decied next state exp - 1 byte 
                            if (r_Bit_Index <7 )
                            begin
                                r_Bit_Index <= r_Bit_Index +1; 
                                r_SM_Main <= RX_DATA_BIT; 
                            end
                            else
                            begin
                                r_Bit_Index <=0 ; 
                                r_SM_Main <= RX_STOP_BIT;  // State transitino because all data bytes have been recieved
                            end
                        end
                    end
                RX_STOP_BIT:
                    begin
                        //waiting CLKS_PER_BUT-1 clock cycles for stop bit to finish
                        if (r_Clock_Count < CLKS_PER_BIT-1)
                        begin
                            r_Clock_Count <= r_Clock_Count+1; 
                            r_SM_Main <= RX_STOP_BIT; 
                        end
                        else
                        begin
                            r_RX_DV   <= 1'b1; //indicating data value has been recieved
                            r_SM_Main <= CLEANUP; 
                        end
                    end
                CLEANUP:
                    begin
                        // Resetting State and data value
                        r_SM_Main <= IDLE; 
                        r_RX_DV <= 1'b0; 

                    end
        endcase
    end

    assign o_RX_DV = r_RX_DV; 
    assign o_RX_Byte = r_RX_Byte; 


    
endmodule

UART_RX_tb.v
//////////////////////////////////////////////////////////////////////
// File Downloaded from http://www.nandland.com
//////////////////////////////////////////////////////////////////////

// This testbench will exercise the UART RX.
// It sends out byte 0x37, and ensures the RX receives it correctly.
`timescale 1ns/10ps

module UART_RX_TB();

  // Testbench uses a 25 MHz clock (same as Go Board)
  // Want to interface to 115200 baud UART
  // 25000000 / 115200 = 217 Clocks Per Bit.
  parameter c_CLOCK_PERIOD_NS = 40;
  parameter c_CLKS_PER_BIT    = 217;
  parameter c_BIT_PERIOD      = 8600;
  
  reg r_Clock = 0;
  reg r_RX_Serial = 1;
  wire [7:0] w_RX_Byte;
  

  // Takes in input byte and serializes it 
  task UART_WRITE_BYTE;
    input [7:0] i_Data;
    integer     ii;
    begin
      
      // Send Start Bit
      r_RX_Serial <= 1'b0;
      #(c_BIT_PERIOD);
      #1000;
      
      // Send Data Byte
      for (ii=0; ii<8; ii=ii+1)
        begin
          r_RX_Serial <= i_Data[ii];
          #(c_BIT_PERIOD);
        end
      
      // Send Stop Bit
      r_RX_Serial <= 1'b1;
      #(c_BIT_PERIOD);
     end
  endtask // UART_WRITE_BYTE
  
  
  UART_RX #(.CLKS_PER_BIT(c_CLKS_PER_BIT)) UART_RX_INST
    (.i_Clk(r_Clock),
     .i_RX_Serial(r_RX_Serial),
     .o_RX_DV(),
     .o_RX_Byte(w_RX_Byte)
     );
  
  always
    #(c_CLOCK_PERIOD_NS/2) r_Clock <= !r_Clock;

  
  // Main Testing:
  initial
    begin
    // Dumpfiles 
      $dumpfile("_build/default/UART_RX_tb.vcd");
      $dumpvars(0, UART_RX_TB);
      // Send a command to the UART (exercise Rx)
      @(posedge r_Clock);
      UART_WRITE_BYTE(8'h37);
      @(posedge r_Clock);
            
      // Check that the correct command was received
      if (w_RX_Byte == 8'h37)
        $display("Test Passed - Correct Byte Received");
      else
        $display("Test Failed - Incorrect Byte Received");
    $finish();
    end
    
  


  
endmodule

_build/default/UART_RX_tb.vcd
$date
	Sat Nov  1 15:17:28 2025
$end
$version
	Icarus Verilog
$end
$timescale
	1ps
$end
$scope module UART_RX_TB $end
$var wire 8 ! w_RX_Byte [7:0] $end
$var parameter 32 " c_BIT_PERIOD $end
$var parameter 32 # c_CLKS_PER_BIT $end
$var parameter 32 $ c_CLOCK_PERIOD_NS $end
$var reg 1 % r_Clock $end
$var reg 1 & r_RX_Serial $end
$scope module UART_RX_INST $end
$var wire 1 % i_Clk $end
$var wire 1 & i_RX_Serial $end
$var wire 8 ' o_RX_Byte [7:0] $end
$var wire 1 ( o_RX_DV $end
$var parameter 3 ) CLEANUP $end
$var parameter 32 * CLKS_PER_BIT $end
$var parameter 3 + IDLE $end
$var parameter 3 , RX_DATA_BIT $end
$var parameter 3 - RX_START_BIT $end
$var parameter 3 . RX_STOP_BIT $end
$var reg 3 / r_Bit_Index [2:0] $end
$var reg 8 0 r_Clock_Count [7:0] $end
$var reg 8 1 r_RX_Byte [7:0] $end
$var reg 1 2 r_RX_DV $end
$var reg 3 3 r_SM_Main [2:0] $end
$upscope $end
$scope task UART_WRITE_BYTE $end
$var reg 8 4 i_Data [7:0] $end
$var integer 32 5 ii [31:0] $end
$upscope $end
$upscope $end
$enddefinitions $end
$comment Show the parameter values. $end
$dumpall
b11 .
b1 -
b10 ,
b0 +
b11011001 *
b100 )
b101000 $
b11011001 #
b10000110011000 "
$end
#0
$dumpvars
bx 5
bx 4
b0 3
02
b0 1
b0 0
b0 /
0(
b0 '
1&
0%
b0 !
$end
#20000
0&
b110111 4
1%
#40000
0%
#60000
b1 3
1%
#80000
0%
#100000
b1 0
1%
#120000
0%
#140000
b10 0
1%
#160000
0%
#180000
b11 0
1%
#200000
0%
#220000
b100 0
1%
#240000
0%
#260000
b101 0
1%
#280000
0%
#300000
b110 0
1%
#320000
0%
#340000
b111 0
1%
#360000
0%
#380000
b1000 0
1%
#400000
0%
#420000
b1001 0
1%
#440000
0%
#460000
b1010 0
1%
#480000
0%
#500000
b1011 0
1%
#520000
0%
#540000
b1100 0
1%
#560000
0%
#580000
b1101 0
1%
#600000
0%
#620000
b1110 0
1%
#640000
0%
#660000
b1111 0
1%
#680000
0%
#700000
b10000 0
1%
#720000
0%
#740000
b10001 0
1%
#760000
0%
#780000
b10010 0
1%
#800000
0%
#820000
b10011 0
1%
#840000
0%
#860000
b10100 0
1%
#880000
0%
#900000
b10101 0
1%
#920000
0%
#940000
b10110 0
1%
#960000
0%
#980000
b10111 0
1%
#1000000
0%
#1020000
b11000 0
1%
#1040000
0%
#1060000
b11001 0
1%
#1080000
0%
#1100000
b11010 0
1%
#1120000
0%
#1140000
b11011 0
1%
#1160000
0%
#1180000
b11100 0
1%
#1200000
0%
#1220000
b11101 0
1%
#1240000
0%
#1260000
b11110 0
1%
#1280000
0%
#1300000
b11111 0
1%
#1320000
0%
#1340000
b100000 0
1%
#1360000
0%
#1380000
b100001 0
1%
#1400000
0%
#1420000
b100010 0
1%
#1440000
0%
#1460000
b100011 0
1%
#1480000
0%
#1500000
b100100 0
1%
#1520000
0%
#1540000
b100101 0
1%
#1560000
0%
#1580000
b100110 0
1%
#1600000
0%
#1620000
b100111 0
1%
#1640000
0%
#1660000
b101000 0
1%
#1680000
0%
#1700000
b101001 0
1%
#1720000
0%
#1740000
b101010 0
1%
#1760000
0%
#1780000
b101011 0
1%
#1800000
0%
#1820000
b101100 0
1%
#1840000
0%
#1860000
b101101 0
1%
#1880000
0%
#1900000
b101110 0
1%
#1920000
0%
#1940000
b101111 0
1%
#1960000
0%
#1980000
b110000 0
1%
#2000000
0%
#2020000
b110001 0
1%
#2040000
0%
#2060000
b110010 0
1%
#2080000
0%
#2100000
b110011 0
1%
#2120000
0%
#2140000
b110100 0
1%
#2160000
0%
#2180000
b110101 0
1%
#2200000
0%
#2220000
b110110 0
1%
#2240000
0%
#2260000
b110111 0
1%
#2280000
0%
#2300000
b111000 0
1%
#2320000
0%
#2340000
b111001 0
1%
#2360000
0%
#2380000
b111010 0
1%
#2400000
0%
#2420000
b111011 0
1%
#2440000
0%
#2460000
b111100 0
1%
#2480000
0%
#2500000
b111101 0
1%
#2520000
0%
#2540000
b111110 0
1%
#2560000
0%
#2580000
b111111 0
1%
#2600000
0%
#2620000
b1000000 0
1%
#2640000
0%
#2660000
b1000001 0
1%
#2680000
0%
#2700000
b1000010 0
1%
#2720000
0%
#2740000
b1000011 0
1%
#2760000
0%
#2780000
b1000100 0
1%
#2800000
0%
#2820000
b1000101 0
1%
#2840000
0%
#2860000
b1000110 0
1%
#2880000
0%
#2900000
b1000111 0
1%
#2920000
0%
#2940000
b1001000 0
1%
#2960000
0%
#2980000
b1001001 0
1%
#3000000
0%
#3020000
b1001010 0
1%
#3040000
0%
#3060000
b1001011 0
1%
#3080000
0%
#3100000
b1001100 0
1%
#3120000
0%
#3140000
b1001101 0
1%
#3160000
0%
#3180000
b1001110 0
1%
#3200000
0%
#3220000
b1001111 0
1%
#3240000
0%
#3260000
b1010000 0
1%
#3280000
0%
#3300000
b1010001 0
1%
#3320000
0%
#3340000
b1010010 0
1%
#3360000
0%
#3380000
b1010011 0
1%
#3400000
0%
#3420000
b1010100 0
1%
#3440000
0%
#3460000
b1010101 0
1%
#3480000
0%
#3500000
b1010110 0
1%
#3520000
0%
#3540000
b1010111 0
1%
#3560000
0%
#3580000
b1011000 0
1%
#3600000
0%
#3620000
b1011001 0
1%
#3640000
0%
#3660000
b1011010 0
1%
#3680000
0%
#3700000
b1011011 0
1%
#3720000
0%
#3740000
b1011100 0
1%
#3760000
0%
#3780000
b1011101 0
1%
#3800000
0%
#3820000
b1011110 0
1%
#3840000
0%
#3860000
b1011111 0
1%
#3880000
0%
#3900000
b1100000 0
1%
#3920000
0%
#3940000
b1100001 0
1%
#3960000
0%
#3980000
b1100010 0
1%
#4000000
0%
#4020000
b1100011 0
1%
#4040000
0%
#4060000
b1100100 0
1%
#4080000
0%
#4100000
b1100101 0
1%
#4120000
0%
#4140000
b1100110 0
1%
#4160000
0%
#4180000
b1100111 0
1%
#4200000
0%
#4220000
b1101000 0
1%
#4240000
0%
#4260000
b1101001 0
1%
#4280000
0%
#4300000
b1101010 0
1%
#4320000
0%
#4340000
b1101011 0
1%
#4360000
0%
#4380000
b1101100 0
1%
#4400000
0%
#4420000
b10 3
b0 0
1%
#4440000
0%
#4460000
b1 0
1%
#4480000
0%
#4500000
b10 0
1%
#4520000
0%
#4540000
b11 0
1%
#4560000
0%
#4580000
b100 0
1%
#4600000
0%
#4620000
b101 0
1%
#4640000
0%
#4660000
b110 0
1%
#4680000
0%
#4700000
b111 0
1%
#4720000
0%
#4740000
b1000 0
1%
#4760000
0%
#4780000
b1001 0
1%
#4800000
0%
#4820000
b1010 0
1%
#4840000
0%
#4860000
b1011 0
1%
#4880000
0%
#4900000
b1100 0
1%
#4920000
0%
#4940000
b1101 0
1%
#4960000
0%
#4980000
b1110 0
1%
#5000000
0%
#5020000
b1111 0
1%
#5040000
0%
#5060000
b10000 0
1%
#5080000
0%
#5100000
b10001 0
1%
#5120000
0%
#5140000
b10010 0
1%
#5160000
0%
#5180000
b10011 0
1%
#5200000
0%
#5220000
b10100 0
1%
#5240000
0%
#5260000
b10101 0
1%
#5280000
0%
#5300000
b10110 0
1%
#5320000
0%
#5340000
b10111 0
1%
#5360000
0%
#5380000
b11000 0
1%
#5400000
0%
#5420000
b11001 0
1%
#5440000
0%
#5460000
b11010 0
1%
#5480000
0%
#5500000
b11011 0
1%
#5520000
0%
#5540000
b11100 0
1%
#5560000
0%
#5580000
b11101 0
1%
#5600000
0%
#5620000
b11110 0
1%
#5640000
0%
#5660000
b11111 0
1%
#5680000
0%
#5700000
b100000 0
1%
#5720000
0%
#5740000
b100001 0
1%
#5760000
0%
#5780000
b100010 0
1%
#5800000
0%
#5820000
b100011 0
1%
#5840000
0%
#5860000
b100100 0
1%
#5880000
0%
#5900000
b100101 0
1%
#5920000
0%
#5940000
b100110 0
1%
#5960000
0%
#5980000
b100111 0
1%
#6000000
0%
#6020000
b101000 0
1%
#6040000
0%
#6060000
b101001 0
1%
#6080000
0%
#6100000
b101010 0
1%
#6120000
0%
#6140000
b101011 0
1%
#6160000
0%
#6180000
b101100 0
1%
#6200000
0%
#6220000
b101101 0
1%
#6240000
0%
#6260000
b101110 0
1%
#6280000
0%
#6300000
b101111 0
1%
#6320000
0%
#6340000
b110000 0
1%
#6360000
0%
#6380000
b110001 0
1%
#6400000
0%
#6420000
b110010 0
1%
#6440000
0%
#6460000
b110011 0
1%
#6480000
0%
#6500000
b110100 0
1%
#6520000
0%
#6540000
b110101 0
1%
#6560000
0%
#6580000
b110110 0
1%
#6600000
0%
#6620000
b110111 0
1%
#6640000
0%
#6660000
b111000 0
1%
#6680000
0%
#6700000
b111001 0
1%
#6720000
0%
#6740000
b111010 0
1%
#6760000
0%
#6780000
b111011 0
1%
#6800000
0%
#6820000
b111100 0
1%
#6840000
0%
#6860000
b111101 0
1%
#6880000
0%
#6900000
b111110 0
1%
#6920000
0%
#6940000
b111111 0
1%
#6960000
0%
#6980000
b1000000 0
1%
#7000000
0%
#7020000
b1000001 0
1%
#7040000
0%
#7060000
b1000010 0
1%
#7080000
0%
#7100000
b1000011 0
1%
#7120000
0%
#7140000
b1000100 0
1%
#7160000
0%
#7180000
b1000101 0
1%
#7200000
0%
#7220000
b1000110 0
1%
#7240000
0%
#7260000
b1000111 0
1%
#7280000
0%
#7300000
b1001000 0
1%
#7320000
0%
#7340000
b1001001 0
1%
#7360000
0%
#7380000
b1001010 0
1%
#7400000
0%
#7420000
b1001011 0
1%
#7440000
0%
#7460000
b1001100 0
1%
#7480000
0%
#7500000
b1001101 0
1%
#7520000
0%
#7540000
b1001110 0
1%
#7560000
0%
#7580000
b1001111 0
1%
#7600000
0%
#7620000
b1010000 0
1%
#7640000
0%
#7660000
b1010001 0
1%
#7680000
0%
#7700000
b1010010 0
1%
#7720000
0%
#7740000
b1010011 0
1%
#7760000
0%
#7780000
b1010100 0
1%
#7800000
0%
#7820000
b1010101 0
1%
#7840000
0%
#7860000
b1010110 0
1%
#7880000
0%
#7900000
b1010111 0
1%
#7920000
0%
#7940000
b1011000 0
1%
#7960000
0%
#7980000
b1011001 0
1%
#8000000
0%
#8020000
b1011010 0
1%
#8040000
0%
#8060000
b1011011 0
1%
#8080000
0%
#8100000
b1011100 0
1%
#8120000
0%
#8140000
b1011101 0
1%
#8160000
0%
#8180000
b1011110 0
1%
#8200000
0%
#8220000
b1011111 0
1%
#8240000
0%
#8260000
b1100000 0
1%
#8280000
0%
#8300000
b1100001 0
1%
#8320000
0%
#8340000
b1100010 0
1%
#8360000
0%
#8380000
b1100011 0
1%
#8400000
0%
#8420000
b1100100 0
1%
#8440000
0%
#8460000
b1100101 0
1%
#8480000
0%
#8500000
b1100110 0
1%
#8520000
0%
#8540000
b1100111 0
1%
#8560000
0%
#8580000
b1101000 0
1%
#8600000
0%
#8620000
b1101001 0
1%
#8640000
0%
#8660000
b1101010 0
1%
#8680000
0%
#8700000
b1101011 0
1%
#8720000
0%
#8740000
b1101100 0
1%
#8760000
0%
#8780000
b1101101 0
1%
#8800000
0%
#8820000
b1101110 0
1%
#8840000
0%
#8860000
b1101111 0
1%
#8880000
0%
#8900000
b1110000 0
1%
#8920000
0%
#8940000
b1110001 0
1%
#8960000
0%
#8980000
b1110010 0
1%
#9000000
0%
#9020000
b1110011 0
1%
#9040000
0%
#9060000
b1110100 0
1%
#9080000
0%
#9100000
b1110101 0
1%
#9120000
0%
#9140000
b1110110 0
1%
#9160000
0%
#9180000
b1110111 0
1%
#9200000
0%
#9220000
b1111000 0
1%
#9240000
0%
#9260000
b1111001 0
1%
#9280000
0%
#9300000
b1111010 0
1%
#9320000
0%
#9340000
b1111011 0
1%
#9360000
0%
#9380000
b1111100 0
1%
#9400000
0%
#9420000
b1111101 0
1%
#9440000
0%
#9460000
b1111110 0
1%
#9480000
0%
#9500000
b1111111 0
1%
#9520000
0%
#9540000
b10000000 0
1%
#9560000
0%
#9580000
b10000001 0
1%
#9600000
0%
#9620000
b10000010 0
1%
1&
b0 5
#9640000
0%
#9660000
b10000011 0
1%
#9680000
0%
#9700000
b10000100 0
1%
#9720000
0%
#9740000
b10000101 0
1%
#9760000
0%
#9780000
b10000110 0
1%
#9800000
0%
#9820000
b10000111 0
1%
#9840000
0%
#9860000
b10001000 0
1%
#9880000
0%
#9900000
b10001001 0
1%
#9920000
0%
#9940000
b10001010 0
1%
#9960000
0%
#9980000
b10001011 0
1%
#10000000
0%
#10020000
b10001100 0
1%
#10040000
0%
#10060000
b10001101 0
1%
#10080000
0%
#10100000
b10001110 0
1%
#10120000
0%
#10140000
b10001111 0
1%
#10160000
0%
#10180000
b10010000 0
1%
#10200000
0%
#10220000
b10010001 0
1%
#10240000
0%
#10260000
b10010010 0
1%
#10280000
0%
#10300000
b10010011 0
1%
#10320000
0%
#10340000
b10010100 0
1%
#10360000
0%
#10380000
b10010101 0
1%
#10400000
0%
#10420000
b10010110 0
1%
#10440000
0%
#10460000
b10010111 0
1%
#10480000
0%
#10500000
b10011000 0
1%
#10520000
0%
#10540000
b10011001 0
1%
#10560000
0%
#10580000
b10011010 0
1%
#10600000
0%
#10620000
b10011011 0
1%
#10640000
0%
#10660000
b10011100 0
1%
#10680000
0%
#10700000
b10011101 0
1%
#10720000
0%
#10740000
b10011110 0
1%
#10760000
0%
#10780000
b10011111 0
1%
#10800000
0%
#10820000
b10100000 0
1%
#10840000
0%
#10860000
b10100001 0
1%
#10880000
0%
#10900000
b10100010 0
1%
#10920000
0%
#10940000
b10100011 0
1%
#10960000
0%
#10980000
b10100100 0
1%
#11000000
0%
#11020000
b10100101 0
1%
#11040000
0%
#11060000
b10100110 0
1%
#11080000
0%
#11100000
b10100111 0
1%
#11120000
0%
#11140000
b10101000 0
1%
#11160000
0%
#11180000
b10101001 0
1%
#11200000
0%
#11220000
b10101010 0
1%
#11240000
0%
#11260000
b10101011 0
1%
#11280000
0%
#11300000
b10101100 0
1%
#11320000
0%
#11340000
b10101101 0
1%
#11360000
0%
#11380000
b10101110 0
1%
#11400000
0%
#11420000
b10101111 0
1%
#11440000
0%
#11460000
b10110000 0
1%
#11480000
0%
#11500000
b10110001 0
1%
#11520000
0%
#11540000
b10110010 0
1%
#11560000
0%
#11580000
b10110011 0
1%
#11600000
0%
#11620000
b10110100 0
1%
#11640000
0%
#11660000
b10110101 0
1%
#11680000
0%
#11700000
b10110110 0
1%
#11720000
0%
#11740000
b10110111 0
1%
#11760000
0%
#11780000
b10111000 0
1%
#11800000
0%
#11820000
b10111001 0
1%
#11840000
0%
#11860000
b10111010 0
1%
#11880000
0%
#11900000
b10111011 0
1%
#11920000
0%
#11940000
b10111100 0
1%
#11960000
0%
#11980000
b10111101 0
1%
#12000000
0%
#12020000
b10111110 0
1%
#12040000
0%
#12060000
b10111111 0
1%
#12080000
0%
#12100000
b11000000 0
1%
#12120000
0%
#12140000
b11000001 0
1%
#12160000
0%
#12180000
b11000010 0
1%
#12200000
0%
#12220000
b11000011 0
1%
#12240000
0%
#12260000
b11000100 0
1%
#12280000
0%
#12300000
b11000101 0
1%
#12320000
0%
#12340000
b11000110 0
1%
#12360000
0%
#12380000
b11000111 0
1%
#12400000
0%
#12420000
b11001000 0
1%
#12440000
0%
#12460000
b11001001 0
1%
#12480000
0%
#12500000
b11001010 0
1%
#12520000
0%
#12540000
b11001011 0
1%
#12560000
0%
#12580000
b11001100 0
1%
#12600000
0%
#12620000
b11001101 0
1%
#12640000
0%
#12660000
b11001110 0
1%
#12680000
0%
#12700000
b11001111 0
1%
#12720000
0%
#12740000
b11010000 0
1%
#12760000
0%
#12780000
b11010001 0
1%
#12800000
0%
#12820000
b11010010 0
1%
#12840000
0%
#12860000
b11010011 0
1%
#12880000
0%
#12900000
b11010100 0
1%
#12920000
0%
#12940000
b11010101 0
1%
#12960000
0%
#12980000
b11010110 0
1%
#13000000
0%
#13020000
b11010111 0
1%
#13040000
0%
#13060000
b11011000 0
1%
#13080000
0%
#13100000
b1 /
b1 !
b1 '
b1 1
b0 0
1%
#13120000
0%
#13140000
b1 0
1%
#13160000
0%
#13180000
b10 0
1%
#13200000
0%
#13220000
b11 0
1%
#13240000
0%
#13260000
b100 0
1%
#13280000
0%
#13300000
b101 0
1%
#13320000
0%
#13340000
b110 0
1%
#13360000
0%
#13380000
b111 0
1%
#13400000
0%
#13420000
b1000 0
1%
#13440000
0%
#13460000
b1001 0
1%
#13480000
0%
#13500000
b1010 0
1%
#13520000
0%
#13540000
b1011 0
1%
#13560000
0%
#13580000
b1100 0
1%
#13600000
0%
#13620000
b1101 0
1%
#13640000
0%
#13660000
b1110 0
1%
#13680000
0%
#13700000
b1111 0
1%
#13720000
0%
#13740000
b10000 0
1%
#13760000
0%
#13780000
b10001 0
1%
#13800000
0%
#13820000
b10010 0
1%
#13840000
0%
#13860000
b10011 0
1%
#13880000
0%
#13900000
b10100 0
1%
#13920000
0%
#13940000
b10101 0
1%
#13960000
0%
#13980000
b10110 0
1%
#14000000
0%
#14020000
b10111 0
1%
#14040000
0%
#14060000
b11000 0
1%
#14080000
0%
#14100000
b11001 0
1%
#14120000
0%
#14140000
b11010 0
1%
#14160000
0%
#14180000
b11011 0
1%
#14200000
0%
#14220000
b11100 0
1%
#14240000
0%
#14260000
b11101 0
1%
#14280000
0%
#14300000
b11110 0
1%
#14320000
0%
#14340000
b11111 0
1%
#14360000
0%
#14380000
b100000 0
1%
#14400000
0%
#14420000
b100001 0
1%
#14440000
0%
#14460000
b100010 0
1%
#14480000
0%
#14500000
b100011 0
1%
#14520000
0%
#14540000
b100100 0
1%
#14560000
0%
#14580000
b100101 0
1%
#14600000
0%
#14620000
b100110 0
1%
#14640000
0%
#14660000
b100111 0
1%
#14680000
0%
#14700000
b101000 0
1%
#14720000
0%
#14740000
b101001 0
1%
#14760000
0%
#14780000
b101010 0
1%
#14800000
0%
#14820000
b101011 0
1%
#14840000
0%
#14860000
b101100 0
1%
#14880000
0%
#14900000
b101101 0
1%
#14920000
0%
#14940000
b101110 0
1%
#14960000
0%
#14980000
b101111 0
1%
#15000000
0%
#15020000
b110000 0
1%
#15040000
0%
#15060000
b110001 0
1%
#15080000
0%
#15100000
b110010 0
1%
#15120000
0%
#15140000
b110011 0
1%
#15160000
0%
#15180000
b110100 0
1%
#15200000
0%
#15220000
b110101 0
1%
#15240000
0%
#15260000
b110110 0
1%
#15280000
0%
#15300000
b110111 0
1%
#15320000
0%
#15340000
b111000 0
1%
#15360000
0%
#15380000
b111001 0
1%
#15400000
0%
#15420000
b111010 0
1%
#15440000
0%
#15460000
b111011 0
1%
#15480000
0%
#15500000
b111100 0
1%
#15520000
0%
#15540000
b111101 0
1%
#15560000
0%
#15580000
b111110 0
1%
#15600000
0%
#15620000
b111111 0
1%
#15640000
0%
#15660000
b1000000 0
1%
#15680000
0%
#15700000
b1000001 0
1%
#15720000
0%
#15740000
b1000010 0
1%
#15760000
0%
#15780000
b1000011 0
1%
#15800000
0%
#15820000
b1000100 0
1%
#15840000
0%
#15860000
b1000101 0
1%
#15880000
0%
#15900000
b1000110 0
1%
#15920000
0%
#15940000
b1000111 0
1%
#15960000
0%
#15980000
b1001000 0
1%
#16000000
0%
#16020000
b1001001 0
1%
#16040000
0%
#16060000
b1001010 0
1%
#16080000
0%
#16100000
b1001011 0
1%
#16120000
0%
#16140000
b1001100 0
1%
#16160000
0%
#16180000
b1001101 0
1%
#16200000
0%
#16220000
b1001110 0
1%
#16240000
0%
#16260000
b1001111 0
1%
#16280000
0%
#16300000
b1010000 0
1%
#16320000
0%
#16340000
b1010001 0
1%
#16360000
0%
#16380000
b1010010 0
1%
#16400000
0%
#16420000
b1010011 0
1%
#16440000
0%
#16460000
b1010100 0
1%
#16480000
0%
#16500000
b1010101 0
1%
#16520000
0%
#16540000
b1010110 0
1%
#16560000
0%
#16580000
b1010111 0
1%
#16600000
0%
#16620000
b1011000 0
1%
#16640000
0%
#16660000
b1011001 0
1%
#16680000
0%
#16700000
b1011010 0
1%
#16720000
0%
#16740000
b1011011 0
1%
#16760000
0%
#16780000
b1011100 0
1%
#16800000
0%
#16820000
b1011101 0
1%
#16840000
0%
#16860000
b1011110 0
1%
#16880000
0%
#16900000
b1011111 0
1%
#16920000
0%
#16940000
b1100000 0
1%
#16960000
0%
#16980000
b1100001 0
1%
#17000000
0%
#17020000
b1100010 0
1%
#17040000
0%
#17060000
b1100011 0
1%
#17080000
0%
#17100000
b1100100 0
1%
#17120000
0%
#17140000
b1100101 0
1%
#17160000
0%
#17180000
b1100110 0
1%
#17200000
0%
#17220000
b1100111 0
1%
#17240000
0%
#17260000
b1101000 0
1%
#17280000
0%
#17300000
b1101001 0
1%
#17320000
0%
#17340000
b1101010 0
1%
#17360000
0%
#17380000
b1101011 0
1%
#17400000
0%
#17420000
b1101100 0
1%
#17440000
0%
#17460000
b1101101 0
1%
#17480000
0%
#17500000
b1101110 0
1%
#17520000
0%
#17540000
b1101111 0
1%
#17560000
0%
#17580000
b1110000 0
1%
#17600000
0%
#17620000
b1110001 0
1%
#17640000
0%
#17660000
b1110010 0
1%
#17680000
0%
#17700000
b1110011 0
1%
#17720000
0%
#17740000
b1110100 0
1%
#17760000
0%
#17780000
b1110101 0
1%
#17800000
0%
#17820000
b1110110 0
1%
#17840000
0%
#17860000
b1110111 0
1%
#17880000
0%
#17900000
b1111000 0
1%
#17920000
0%
#17940000
b1111001 0
1%
#17960000
0%
#17980000
b1111010 0
1%
#18000000
0%
#18020000
b1111011 0
1%
#18040000
0%
#18060000
b1111100 0
1%
#18080000
0%
#18100000
b1111101 0
1%
#18120000
0%
#18140000
b1111110 0
1%
#18160000
0%
#18180000
b1111111 0
1%
#18200000
0%
#18220000
b10000000 0
1%
b1 5
#18240000
0%
#18260000
b10000001 0
1%
#18280000
0%
#18300000
b10000010 0
1%
#18320000
0%
#18340000
b10000011 0
1%
#18360000
0%
#18380000
b10000100 0
1%
#18400000
0%
#18420000
b10000101 0
1%
#18440000
0%
#18460000
b10000110 0
1%
#18480000
0%
#18500000
b10000111 0
1%
#18520000
0%
#18540000
b10001000 0
1%
#18560000
0%
#18580000
b10001001 0
1%
#18600000
0%
#18620000
b10001010 0
1%
#18640000
0%
#18660000
b10001011 0
1%
#18680000
0%
#18700000
b10001100 0
1%
#18720000
0%
#18740000
b10001101 0
1%
#18760000
0%
#18780000
b10001110 0
1%
#18800000
0%
#18820000
b10001111 0
1%
#18840000
0%
#18860000
b10010000 0
1%
#18880000
0%
#18900000
b10010001 0
1%
#18920000
0%
#18940000
b10010010 0
1%
#18960000
0%
#18980000
b10010011 0
1%
#19000000
0%
#19020000
b10010100 0
1%
#19040000
0%
#19060000
b10010101 0
1%
#19080000
0%
#19100000
b10010110 0
1%
#19120000
0%
#19140000
b10010111 0
1%
#19160000
0%
#19180000
b10011000 0
1%
#19200000
0%
#19220000
b10011001 0
1%
#19240000
0%
#19260000
b10011010 0
1%
#19280000
0%
#19300000
b10011011 0
1%
#19320000
0%
#19340000
b10011100 0
1%
#19360000
0%
#19380000
b10011101 0
1%
#19400000
0%
#19420000
b10011110 0
1%
#19440000
0%
#19460000
b10011111 0
1%
#19480000
0%
#19500000
b10100000 0
1%
#19520000
0%
#19540000
b10100001 0
1%
#19560000
0%
#19580000
b10100010 0
1%
#19600000
0%
#19620000
b10100011 0
1%
#19640000
0%
#19660000
b10100100 0
1%
#19680000
0%
#19700000
b10100101 0
1%
#19720000
0%
#19740000
b10100110 0
1%
#19760000
0%
#19780000
b10100111 0
1%
#19800000
0%
#19820000
b10101000 0
1%
#19840000
0%
#19860000
b10101001 0
1%
#19880000
0%
#19900000
b10101010 0
1%
#19920000
0%
#19940000
b10101011 0
1%
#19960000
0%
#19980000
b10101100 0
1%
#20000000
0%
#20020000
b10101101 0
1%
#20040000
0%
#20060000
b10101110 0
1%
#20080000
0%
#20100000
b10101111 0
1%
#20120000
0%
#20140000
b10110000 0
1%
#20160000
0%
#20180000
b10110001 0
1%
#20200000
0%
#20220000
b10110010 0
1%
#20240000
0%
#20260000
b10110011 0
1%
#20280000
0%
#20300000
b10110100 0
1%
#20320000
0%
#20340000
b10110101 0
1%
#20360000
0%
#20380000
b10110110 0
1%
#20400000
0%
#20420000
b10110111 0
1%
#20440000
0%
#20460000
b10111000 0
1%
#20480000
0%
#20500000
b10111001 0
1%
#20520000
0%
